<?xml version='1.0' encoding='utf-8'?>
<!DOCTYPE hibernate-configuration PUBLIC
        "-//hibernate/hibernate Configuration DTD//EN"
        "http://www.hibernate.org/dtd/hibernate-configuration-3.0.dtd">
<hibernate-configuration>
    <session-factory>
        <property name="hibernate.hbm2ddl.auto">update</property>
        <property name="connection.url">jdbc:postgresql://10.0.2.15/postgres</property>
        <property name="connection.driver_class">org.postgresql.Driver</property>
        <property name="connection.username">postgres</property>
        <property name="connection.password">postgres</property>
        <property name="hibernate.dialect">org.hibernate.dialect.PostgresPlusDialect</property>
        <property name="hibernate.show_sql">false</property>
        <property name="hibernate.format_sql">false</property>

        <mapping class="main.java.app.model.Coche"/>
        <mapping class="main.java.app.model.Multa"/>
    </session-factory>
</hibernate-configuration>